depend/__init__.py
depend/__main__.py
depend/api_handler.py
depend/caching_client.py
depend/cli.py
depend/constants.py
depend/dep.py
depend/errors.py
depend/helper.py
depend/resolver.py
depend/parser/__init__.py
depend/parser/go.py
depend/parser/js.py
depend/parser/php.py
depend/parser/rust.py
depend/parser/py/__init__.py
depend/parser/py/setup_reader.py
depend/plugins/__init__.py
depend/plugins/license.py
depend/utils/__init__.py
depend/utils/github.py
depend/utils/npm_parser.py
depend/utils/nuspec_parser.py
depend/utils/python.py
depend/vcs/__init__.py
depend/vcs/vcs_helper.py
depend-0.3.0.dist-info/LICENSE
depend-0.3.0.dist-info/METADATA
depend-0.3.0.dist-info/WHEEL
depend-0.3.0.dist-info/entry_points.txt
depend-0.3.0.dist-info/top_level.txt
depend-0.3.0.dist-info/RECORD
